__init__.py
orchardmanagementpackage/__init__.py
orchardmanagementpackage/fruit_info_operation.py
orchardmanagementpackage/inventory_operation.py
orchardmanagementpackage/main.py
orchardmanagementpackage/plantation_operation.py
orchardmanagementpackage/sales_operation.py
orchardmanagementpackage/management/__init__.py
orchardmanagementpackage/management/inventory.py
orchardmanagementpackage/management/sales.py
orchardmanagementpackage/production/__init__.py
orchardmanagementpackage/production/fruit_info.py
orchardmanagementpackage/production/plantation.py
orchardmanagementCL-0.0.9.dist-info/LICENSE.txt
orchardmanagementCL-0.0.9.dist-info/METADATA
orchardmanagementCL-0.0.9.dist-info/WHEEL
orchardmanagementCL-0.0.9.dist-info/top_level.txt
orchardmanagementCL-0.0.9.dist-info/RECORD
